{
	"configurations" : 
	[
		{
			"directories" : 
			[
				{
					"build" : ".",
					"hasInstallRule" : true,
					"jsonFile" : "directory-.-Release-05c7b701aaba6a4d7157.json",
					"minimumCMakeVersion" : 
					{
						"string" : "3.16"
					},
					"projectIndex" : 0,
					"source" : ".",
					"targetIndexes" : 
					[
						0,
						1,
						2,
						3,
						4,
						5,
						6,
						7,
						8,
						9,
						10,
						11,
						12,
						13,
						14,
						15,
						16,
						17,
						18
					]
				}
			],
			"name" : "Release",
			"projects" : 
			[
				{
					"directoryIndexes" : 
					[
						0
					],
					"name" : "palestradigitale",
					"targetIndexes" : 
					[
						0,
						1,
						2,
						3,
						4,
						5,
						6,
						7,
						8,
						9,
						10,
						11,
						12,
						13,
						14,
						15,
						16,
						17,
						18
					]
				}
			],
			"targets" : 
			[
				{
					"directoryIndex" : 0,
					"id" : "all_aotstats::@6890427a1f51a3e7e1df",
					"jsonFile" : "target-all_aotstats-Release-93492b847ad42968a4e1.json",
					"name" : "all_aotstats",
					"projectIndex" : 0
				},
				{
					"directoryIndex" : 0,
					"id" : "all_qmllint::@6890427a1f51a3e7e1df",
					"jsonFile" : "target-all_qmllint-Release-c036a503a944305bc76b.json",
					"name" : "all_qmllint",
					"projectIndex" : 0
				},
				{
					"directoryIndex" : 0,
					"id" : "all_qmllint_json::@6890427a1f51a3e7e1df",
					"jsonFile" : "target-all_qmllint_json-Release-b549b9be8b386fdf88af.json",
					"name" : "all_qmllint_json",
					"projectIndex" : 0
				},
				{
					"directoryIndex" : 0,
					"id" : "all_qmllint_module::@6890427a1f51a3e7e1df",
					"jsonFile" : "target-all_qmllint_module-Release-c2d30e3ee173d69a0a09.json",
					"name" : "all_qmllint_module",
					"projectIndex" : 0
				},
				{
					"directoryIndex" : 0,
					"id" : "all_qmltyperegistrations::@6890427a1f51a3e7e1df",
					"jsonFile" : "target-all_qmltyperegistrations-Release-4657042e3ff52554a8e0.json",
					"name" : "all_qmltyperegistrations",
					"projectIndex" : 0
				},
				{
					"directoryIndex" : 0,
					"id" : "apppalestradigitale::@6890427a1f51a3e7e1df",
					"jsonFile" : "target-apppalestradigitale-Release-66d96e8a362b6c185eea.json",
					"name" : "apppalestradigitale",
					"projectIndex" : 0
				},
				{
					"directoryIndex" : 0,
					"id" : "apppalestradigitale_autogen::@6890427a1f51a3e7e1df",
					"jsonFile" : "target-apppalestradigitale_autogen-Release-9a5d641fbed9a43dccf5.json",
					"name" : "apppalestradigitale_autogen",
					"projectIndex" : 0
				},
				{
					"directoryIndex" : 0,
					"id" : "apppalestradigitale_autogen_timestamp_deps::@6890427a1f51a3e7e1df",
					"jsonFile" : "target-apppalestradigitale_autogen_timestamp_deps-Release-79c8952822772d403fde.json",
					"name" : "apppalestradigitale_autogen_timestamp_deps",
					"projectIndex" : 0
				},
				{
					"directoryIndex" : 0,
					"id" : "apppalestradigitale_copy_qml::@6890427a1f51a3e7e1df",
					"jsonFile" : "target-apppalestradigitale_copy_qml-Release-1f1b51878e0546df6376.json",
					"name" : "apppalestradigitale_copy_qml",
					"projectIndex" : 0
				},
				{
					"directoryIndex" : 0,
					"id" : "apppalestradigitale_copy_res::@6890427a1f51a3e7e1df",
					"jsonFile" : "target-apppalestradigitale_copy_res-Release-fbfa6c5b29845a00d562.json",
					"name" : "apppalestradigitale_copy_res",
					"projectIndex" : 0
				},
				{
					"directoryIndex" : 0,
					"id" : "apppalestradigitale_qmlimportscan::@6890427a1f51a3e7e1df",
					"jsonFile" : "target-apppalestradigitale_qmlimportscan-Release-6080357fd6970e58610e.json",
					"name" : "apppalestradigitale_qmlimportscan",
					"projectIndex" : 0
				},
				{
					"directoryIndex" : 0,
					"id" : "apppalestradigitale_qmllint::@6890427a1f51a3e7e1df",
					"jsonFile" : "target-apppalestradigitale_qmllint-Release-f26667c10114b742b073.json",
					"name" : "apppalestradigitale_qmllint",
					"projectIndex" : 0
				},
				{
					"directoryIndex" : 0,
					"id" : "apppalestradigitale_qmllint_json::@6890427a1f51a3e7e1df",
					"jsonFile" : "target-apppalestradigitale_qmllint_json-Release-205bfb14ce9e69cf41ff.json",
					"name" : "apppalestradigitale_qmllint_json",
					"projectIndex" : 0
				},
				{
					"directoryIndex" : 0,
					"id" : "apppalestradigitale_qmllint_module::@6890427a1f51a3e7e1df",
					"jsonFile" : "target-apppalestradigitale_qmllint_module-Release-bca7c26393a9bccfba8a.json",
					"name" : "apppalestradigitale_qmllint_module",
					"projectIndex" : 0
				},
				{
					"directoryIndex" : 0,
					"id" : "apppalestradigitale_qmltyperegistration::@6890427a1f51a3e7e1df",
					"jsonFile" : "target-apppalestradigitale_qmltyperegistration-Release-efaa315c69e08bc41e22.json",
					"name" : "apppalestradigitale_qmltyperegistration",
					"projectIndex" : 0
				},
				{
					"directoryIndex" : 0,
					"id" : "clean_qml_context_properties::@6890427a1f51a3e7e1df",
					"jsonFile" : "target-clean_qml_context_properties-Release-c76d2ec4fe4474cec5c0.json",
					"name" : "clean_qml_context_properties",
					"projectIndex" : 0
				},
				{
					"directoryIndex" : 0,
					"id" : "dump_qml_context_properties::@6890427a1f51a3e7e1df",
					"jsonFile" : "target-dump_qml_context_properties-Release-dba8c313052179ce85f5.json",
					"name" : "dump_qml_context_properties",
					"projectIndex" : 0
				},
				{
					"directoryIndex" : 0,
					"id" : "generate_qmlls_build_ini_file::@6890427a1f51a3e7e1df",
					"jsonFile" : "target-generate_qmlls_build_ini_file-Release-20425d0296d3c2a726f6.json",
					"name" : "generate_qmlls_build_ini_file",
					"projectIndex" : 0
				},
				{
					"directoryIndex" : 0,
					"id" : "module_apppalestradigitale_aotstats_target::@6890427a1f51a3e7e1df",
					"jsonFile" : "target-module_apppalestradigitale_aotstats_target-Release-98a6cbe4686c098ab8e0.json",
					"name" : "module_apppalestradigitale_aotstats_target",
					"projectIndex" : 0
				}
			]
		}
	],
	"kind" : "codemodel",
	"paths" : 
	{
		"build" : "C:/Users/lapax/Documents/REPO UNI/uni_proj_traccia1/palestradigitale/build/Desktop_Qt_6_11_0_MinGW_64_bit-Release",
		"source" : "C:/Users/lapax/Documents/REPO UNI/uni_proj_traccia1/palestradigitale"
	},
	"version" : 
	{
		"major" : 2,
		"minor" : 7
	}
}
